organo/__init__.py
organo/configs/__init__.py
organo/configs/checkpoint.py
organo/configs/config.py
organo/configs/data_module.py
organo/configs/dataloader.py
organo/configs/init_config.py
organo/configs/logger.py
organo/configs/trainer.py
organo/data/__init__.py
organo/data/datamodule.py
organo/data/utils/__init__.py
organo/loggers/__init__.py
organo/registers.py
organo/registries/__init__.py
organo/registries/module_registry.py
organo/tasks/__init__.py
organo/tasks/fsmn.py
organo/train.py
organo-0.1.0.dist-info/METADATA
organo-0.1.0.dist-info/WHEEL
organo-0.1.0.dist-info/RECORD
