Metadata-Version: 2.3
Name: organo
Version: 0.1.0
Summary: 
Author: migo
Author-email: 1695587905@qq.com
Requires-Python: >=3.10,<3.13
Classifier: Programming Language :: Python :: 3
Classifier: Programming Language :: Python :: 3.10
Classifier: Programming Language :: Python :: 3.11
Classifier: Programming Language :: Python :: 3.12
Requires-Dist: aiohttp (>=3.12.15,<4.0.0)
Requires-Dist: datasets (>=4.0.0,<5.0.0)
Requires-Dist: fsspec (==2025.3.0)
Requires-Dist: hydra-core (>=1.3.2,<2.0.0)
Requires-Dist: lightning (==2.3.3)
Requires-Dist: numpy (==1.26.4)
Requires-Dist: omegaconf (>=2.3.0,<3.0.0)
Requires-Dist: pandas (==2.2.3)
Requires-Dist: phx-class-registry (==5.0.0)
Requires-Dist: s3fs (==2025.3.0)
Requires-Dist: scipy (==1.14.1)
Requires-Dist: torch (==2.3.1)
Requires-Dist: torchmetrics (>=1.0.0,<2.0.0)
Requires-Dist: tqdm (>=4.67.0)
Requires-Dist: typer (>=0.15.1)
Requires-Dist: wandb (>=0.19.8,<0.20.0)
Requires-Dist: yarl (>=1.20.1,<2.0.0)
